PygameBuiltins/__init__.py
PygameBuiltins/buttons.py
PygameBuiltins/particles.py
PygameBuiltins/utils.py
PygameBuiltins-0.2.0.dist-info/LICENSE
PygameBuiltins-0.2.0.dist-info/METADATA
PygameBuiltins-0.2.0.dist-info/WHEEL
PygameBuiltins-0.2.0.dist-info/top_level.txt
PygameBuiltins-0.2.0.dist-info/RECORD
