Metadata-Version: 2.1
Name: PygameBuiltins
Version: 0.2.0
Summary: A pygame wrapper
Author: MrCatNerd#0669
License: MIT
License-File: LICENSE
Requires-Dist: pygame-ce
